openface/__init__.py
openface/cli.py
openface/demo.py
openface/face_detection.py
openface/landmark_detection.py
openface/multitask_model.py
openface/Pytorch_Retinaface/LICENSE.MIT
openface/Pytorch_Retinaface/README.md
openface/Pytorch_Retinaface/convert_to_onnx.py
openface/Pytorch_Retinaface/detect.py
openface/Pytorch_Retinaface/test_fddb.py
openface/Pytorch_Retinaface/test_widerface.py
openface/Pytorch_Retinaface/train.py
openface/Pytorch_Retinaface/__pycache__/detect.cpython-311.pyc
openface/Pytorch_Retinaface/data/__init__.py
openface/Pytorch_Retinaface/data/config.py
openface/Pytorch_Retinaface/data/data_augment.py
openface/Pytorch_Retinaface/data/wider_face.py
openface/Pytorch_Retinaface/data/FDDB/img_list.txt
openface/Pytorch_Retinaface/data/__pycache__/__init__.cpython-311.pyc
openface/Pytorch_Retinaface/data/__pycache__/config.cpython-311.pyc
openface/Pytorch_Retinaface/data/__pycache__/data_augment.cpython-311.pyc
openface/Pytorch_Retinaface/data/__pycache__/wider_face.cpython-311.pyc
openface/Pytorch_Retinaface/layers/__init__.py
openface/Pytorch_Retinaface/layers/__pycache__/__init__.cpython-311.pyc
openface/Pytorch_Retinaface/layers/functions/prior_box.py
openface/Pytorch_Retinaface/layers/functions/__pycache__/prior_box.cpython-311.pyc
openface/Pytorch_Retinaface/layers/modules/__init__.py
openface/Pytorch_Retinaface/layers/modules/multibox_loss.py
openface/Pytorch_Retinaface/layers/modules/__pycache__/__init__.cpython-311.pyc
openface/Pytorch_Retinaface/layers/modules/__pycache__/multibox_loss.cpython-311.pyc
openface/Pytorch_Retinaface/models/__init__.py
openface/Pytorch_Retinaface/models/net.py
openface/Pytorch_Retinaface/models/retinaface.py
openface/Pytorch_Retinaface/models/__pycache__/__init__.cpython-311.pyc
openface/Pytorch_Retinaface/models/__pycache__/net.cpython-311.pyc
openface/Pytorch_Retinaface/models/__pycache__/retinaface.cpython-311.pyc
openface/Pytorch_Retinaface/utils/__init__.py
openface/Pytorch_Retinaface/utils/box_utils.py
openface_test-0.1.26.dist-info/METADATA
openface_test-0.1.26.dist-info/WHEEL
openface_test-0.1.26.dist-info/entry_points.txt
openface_test-0.1.26.dist-info/top_level.txt
openface_test-0.1.26.dist-info/RECORD
