Metadata-Version: 2.4
Name: openface-test
Version: 0.1.26
Requires-Dist: click==8.1.7
Requires-Dist: huggingface_hub==0.21.0
Requires-Dist: imageio==2.34.2
Requires-Dist: matplotlib==3.10.1
Requires-Dist: numpy==1.26.4
Requires-Dist: opencv_contrib_python==4.11.0.86
Requires-Dist: opencv_python==4.11.0.86
Requires-Dist: pandas==2.2.3
Requires-Dist: Pillow==9.4.0
Requires-Dist: scipy==1.13
Requires-Dist: seaborn==0.13.2
Requires-Dist: scikit-image
Requires-Dist: tensorboardX==2.6.2.2
Requires-Dist: timm==1.0.15
Requires-Dist: torch
Requires-Dist: torchvision
Requires-Dist: tqdm==4.66.2
Dynamic: requires-dist
